README
setup.py
pysrvx/__init__.py
pysrvx/authserv.py
pysrvx/chanserv.py
pysrvx/helpserv.py
pysrvx/opserv.py
pysrvx/srvx.py
pysrvx.egg-info/PKG-INFO
pysrvx.egg-info/SOURCES.txt
pysrvx.egg-info/dependency_links.txt
pysrvx.egg-info/top_level.txt
pysrvx.egg-info/zip-safe