Metadata-Version: 1.0
Name: pysrvx
Version: 0.2
Summary: QServer client library
Home-page: http://github.com/GameSurge/pysrvx/
Author: Gavin M. Roy
Author-email: gmr@gamesurge.net
License: BSD
Platform: UNKNOWN
Classifier: Development Status :: 3 - Alpha
Classifier: Intended Audience :: Developers
Classifier: License :: OSI Approved :: GNU General Public License (GPL)
Classifier: License :: OSI Approved :: Mozilla Public License 1.1 (MPL 1.1)
Classifier: Operating System :: OS Independent
Classifier: Topic :: Communications
Classifier: Topic :: Internet
Classifier: Topic :: Software Development :: Libraries
